Workbook

Sheet Rate card
A1: FeelCalm rate card (fixed prices, Naira)
A2: Blue cells are inputs. Every other sheet reads from here, so change a price once and it updates everywhere.
A4: Delivery price by distance
A5: Distance zone | B5: Range | C5: Standard (₦) | D5: Express (₦) | E5: Approx. km | F5: Standard ETA (min) | G5: Express ETA (min)
A6: Nearby | B6: Up to 5 km | C6: 1800 | D6: 2800 | E6: 4 | F6: 35 | G6: 20
A7: Across town | B7: 5 to 15 km | C7: 3000 | D7: 4600 | E7: 10 | F7: 60 | G7: 35
A8: Far | B8: 15 to 30 km | C8: 4800 | D8: 7200 | E8: 22 | F8: 100 | G8: 60
A11: Package size surcharge
A12: Package size | B12: Weight limit | C12: Surcharge (₦)
A13: Envelope | B13: Up to 1 kg | C13: 0
A14: Small box | B14: Up to 5 kg | C14: 600
A15: Large box | B15: Up to 15 kg | C15: 1600
A18: Fixed fees and rider share
A19: Item | B19: Value | C19: Note
A20: Service fee (per delivery) | B20: 250 | C20: Added to every delivery
A21: Parcel protection (optional) | B21: 500 | C21: Covers loss or damage up to ₦50,000
A22: Rider share | B22: 0.8 | C22: Share of delivery price plus size surcharge paid to the rider. Fees and protection are excluded.
A24: Assumption: these prices are placeholder rates chosen for the FeelCalm prototype for Lagos. Replace them with your own before launch.

Sheet Price calculator
A1: Price calculator
A2: Yellow cells are the inputs: pick a value from each dropdown. Everything below recalculates.
A4: Your choices | B4: Value
A5: Distance zone | B5: Across town
A6: Speed | B6: Standard
A7: Package size | B7: Small box
A8: Parcel protection | B8: No
A10: Price breakdown | B10: Amount (₦)
A11: Delivery price | B11: =IF($B$6="Express",INDEX('Rate card'!$D$6:$D$8,MATCH($B$5,'Rate card'!$A$6:$A$8,0)),INDEX('Rate card'!$C$6:$C$8,MATCH($B$5,'Rate card'!$A$6:$A$8,0))) -> 3000
A12: Package size surcharge | B12: =INDEX('Rate card'!$C$13:$C$15,MATCH($B$7,'Rate card'!$A$13:$A$15,0)) -> 600
A13: Service fee | B13: ='Rate card'!$B$20 -> 250
A14: Parcel protection | B14: =IF($B$8="Yes",'Rate card'!$B$21,0) -> 0
A15: Total to pay | B15: =SUM(B11:B14) -> 3850
A17: Split and timing | B17: Value
A18: Rider payout | B18: =ROUND((B11+B12)*'Rate card'!$B$22,0) -> 2880
A19: FeelCalm keeps | B19: =B15-B18 -> 970
A20: Estimated delivery time (min) | B20: =IF($B$6="Express",INDEX('Rate card'!$G$6:$G$8,MATCH($B$5,'Rate card'!$A$6:$A$8,0)),INDEX('Rate card'!$F$6:$F$8,MATCH($B$5,'Rate card'!$A$6:$A$8,0))) -> 60
A21: Approx. distance (km) | B21: =INDEX('Rate card'!$E$6:$E$8,MATCH($B$5,'Rate card'!$A$6:$A$8,0)) -> 10
A23: Check: Across town, Standard, Small box, no protection = ₦3,850 total, ₦2,880 to the rider.

Sheet Price matrix
A1: Every fixed price (without optional protection)
A2: All figures are formulas that read the Rate card. Add ₦500 for parcel protection.
A4: Distance zone | B4: Speed | C4: Package size | D4: Delivery (₦) | E4: Size surcharge (₦) | F4: Service fee (₦) | G4: Total (₦) | H4: Rider payout (₦)
A5: Nearby | B5: Standard | C5: Envelope | D5: =IF($B5="Express",INDEX('Rate card'!$D$6:$D$8,MATCH($A5,'Rate card'!$A$6:$A$8,0)),INDEX('Rate card'!$C$6:$C$8,MATCH($A5,'Rate card'!$A$6:$A$8,0))) -> 1800 | E5: =INDEX('Rate card'!$C$13:$C$15,MATCH($C5,'Rate card'!$A$13:$A$15,0)) -> 0 | F5: ='Rate card'!$B$20 -> 250 | G5: =SUM(D5:F5) -> 2050 | H5: =ROUND((D5+E5)*'Rate card'!$B$22,0) -> 1440
A6: Nearby | B6: Standard | C6: Small box | D6: =IF($B6="Express",INDEX('Rate card'!$D$6:$D$8,MATCH($A6,'Rate card'!$A$6:$A$8,0)),INDEX('Rate card'!$C$6:$C$8,MATCH($A6,'Rate card'!$A$6:$A$8,0))) -> 1800 | E6: =INDEX('Rate card'!$C$13:$C$15,MATCH($C6,'Rate card'!$A$13:$A$15,0)) -> 600 | F6: ='Rate card'!$B$20 -> 250 | G6: =SUM(D6:F6) -> 2650 | H6: =ROUND((D6+E6)*'Rate card'!$B$22,0) -> 1920
A7: Nearby | B7: Standard | C7: Large box | D7: =IF($B7="Express",INDEX('Rate card'!$D$6:$D$8,MATCH($A7,'Rate card'!$A$6:$A$8,0)),INDEX('Rate card'!$C$6:$C$8,MATCH($A7,'Rate card'!$A$6:$A$8,0))) -> 1800 | E7: =INDEX('Rate card'!$C$13:$C$15,MATCH($C7,'Rate card'!$A$13:$A$15,0)) -> 1600 | F7: ='Rate card'!$B$20 -> 250 | G7: =SUM(D7:F7) -> 3650 | H7: =ROUND((D7+E7)*'Rate card'!$B$22,0) -> 2720
A8: Nearby | B8: Express | C8: Envelope | D8: =IF($B8="Express",INDEX('Rate card'!$D$6:$D$8,MATCH($A8,'Rate card'!$A$6:$A$8,0)),INDEX('Rate card'!$C$6:$C$8,MATCH($A8,'Rate card'!$A$6:$A$8,0))) -> 2800 | E8: =INDEX('Rate card'!$C$13:$C$15,MATCH($C8,'Rate card'!$A$13:$A$15,0)) -> 0 | F8: ='Rate card'!$B$20 -> 250 | G8: =SUM(D8:F8) -> 3050 | H8: =ROUND((D8+E8)*'Rate card'!$B$22,0) -> 2240
A9: Nearby | B9: Express | C9: Small box | D9: =IF($B9="Express",INDEX('Rate card'!$D$6:$D$8,MATCH($A9,'Rate card'!$A$6:$A$8,0)),INDEX('Rate card'!$C$6:$C$8,MATCH($A9,'Rate card'!$A$6:$A$8,0))) -> 2800 | E9: =INDEX('Rate card'!$C$13:$C$15,MATCH($C9,'Rate card'!$A$13:$A$15,0)) -> 600 | F9: ='Rate card'!$B$20 -> 250 | G9: =SUM(D9:F9) -> 3650 | H9: =ROUND((D9+E9)*'Rate card'!$B$22,0) -> 2720
A10: Nearby | B10: Express | C10: Large box | D10: =IF($B10="Express",INDEX('Rate card'!$D$6:$D$8,MATCH($A10,'Rate card'!$A$6:$A$8,0)),INDEX('Rate card'!$C$6:$C$8,MATCH($A10,'Rate card'!$A$6:$A$8,0))) -> 2800 | E10: =INDEX('Rate card'!$C$13:$C$15,MATCH($C10,'Rate card'!$A$13:$A$15,0)) -> 1600 | F10: ='Rate card'!$B$20 -> 250 | G10: =SUM(D10:F10) -> 4650 | H10: =ROUND((D10+E10)*'Rate card'!$B$22,0) -> 3520
A11: Across town | B11: Standard | C11: Envelope | D11: =IF($B11="Express",INDEX('Rate card'!$D$6:$D$8,MATCH($A11,'Rate card'!$A$6:$A$8,0)),INDEX('Rate card'!$C$6:$C$8,MATCH($A11,'Rate card'!$A$6:$A$8,0))) -> 3000 | E11: =INDEX('Rate card'!$C$13:$C$15,MATCH($C11,'Rate card'!$A$13:$A$15,0)) -> 0 | F11: ='Rate card'!$B$20 -> 250 | G11: =SUM(D11:F11) -> 3250 | H11: =ROUND((D11+E11)*'Rate card'!$B$22,0) -> 2400
A12: Across town | B12: Standard | C12: Small box | D12: =IF($B12="Express",INDEX('Rate card'!$D$6:$D$8,MATCH($A12,'Rate card'!$A$6:$A$8,0)),INDEX('Rate card'!$C$6:$C$8,MATCH($A12,'Rate card'!$A$6:$A$8,0))) -> 3000 | E12: =INDEX('Rate card'!$C$13:$C$15,MATCH($C12,'Rate card'!$A$13:$A$15,0)) -> 600 | F12: ='Rate card'!$B$20 -> 250 | G12: =SUM(D12:F12) -> 3850 | H12: =ROUND((D12+E12)*'Rate card'!$B$22,0) -> 2880
A13: Across town | B13: Standard | C13: Large box | D13: =IF($B13="Express",INDEX('Rate card'!$D$6:$D$8,MATCH($A13,'Rate card'!$A$6:$A$8,0)),INDEX('Rate card'!$C$6:$C$8,MATCH($A13,'Rate card'!$A$6:$A$8,0))) -> 3000 | E13: =INDEX('Rate card'!$C$13:$C$15,MATCH($C13,'Rate card'!$A$13:$A$15,0)) -> 1600 | F13: ='Rate card'!$B$20 -> 250 | G13: =SUM(D13:F13) -> 4850 | H13: =ROUND((D13+E13)*'Rate card'!$B$22,0) -> 3680
A14: Across town | B14: Express | C14: Envelope | D14: =IF($B14="Express",INDEX('Rate card'!$D$6:$D$8,MATCH($A14,'Rate card'!$A$6:$A$8,0)),INDEX('Rate card'!$C$6:$C$8,MATCH($A14,'Rate card'!$A$6:$A$8,0))) -> 4600 | E14: =INDEX('Rate card'!$C$13:$C$15,MATCH($C14,'Rate card'!$A$13:$A$15,0)) -> 0 | F14: ='Rate card'!$B$20 -> 250 | G14: =SUM(D14:F14) -> 4850 | H14: =ROUND((D14+E14)*'Rate card'!$B$22,0) -> 3680
A15: Across town | B15: Express | C15: Small box | D15: =IF($B15="Express",INDEX('Rate card'!$D$6:$D$8,MATCH($A15,'Rate card'!$A$6:$A$8,0)),INDEX('Rate card'!$C$6:$C$8,MATCH($A15,'Rate card'!$A$6:$A$8,0))) -> 4600 | E15: =INDEX('Rate card'!$C$13:$C$15,MATCH($C15,'Rate card'!$A$13:$A$15,0)) -> 600 | F15: ='Rate card'!$B$20 -> 250 | G15: =SUM(D15:F15) -> 5450 | H15: =ROUND((D15+E15)*'Rate card'!$B$22,0) -> 4160
A16: Across town | B16: Express | C16: Large box | D16: =IF($B16="Express",INDEX('Rate card'!$D$6:$D$8,MATCH($A16,'Rate card'!$A$6:$A$8,0)),INDEX('Rate card'!$C$6:$C$8,MATCH($A16,'Rate card'!$A$6:$A$8,0))) -> 4600 | E16: =INDEX('Rate card'!$C$13:$C$15,MATCH($C16,'Rate card'!$A$13:$A$15,0)) -> 1600 | F16: ='Rate card'!$B$20 -> 250 | G16: =SUM(D16:F16) -> 6450 | H16: =ROUND((D16+E16)*'Rate card'!$B$22,0) -> 4960
... A22: Far | B22: Express | C22: Large box | D22: =IF($B22="Express",INDEX('Rate card'!$D$6:$D$8,MATCH($A22,'Rate card'!$A$6:$A$8,0)),INDEX('Rate card'!$C$6:$C$8,MATCH($A22,'Rate card'!$A$6:$A$8,0))) -> 7200 | E22: =INDEX('Rate card'!$C$13:$C$15,MATCH($C22,'Rate card'!$A$13:$A$15,0)) -> 1600 | F22: ='Rate card'!$B$20 -> 250 | G22: =SUM(D22:F22) -> 9050 | H22: =ROUND((D22+E22)*'Rate card'!$B$22,0) -> 7040

Sheet Features
A1: FeelCalm app features
A2: What is in the prototype today. Live locations are simulated until a backend and phone GPS are connected.
A4: App | B4: Feature | C4: What it does
A5: Customer | B5: Sign-up | C5: Name, phone and delivery address.
A6: Customer | B6: Send a parcel | C6: Item, pickup, delivery address, receiver name and phone, distance, size, speed, payment method and a note for the rider.
A7: Customer | B7: Fixed pricing | C7: Full price breakdown shown before booking. No surge pricing.
A8: Customer | B8: Payment choice | C8: Card, bank transfer or cash to the rider.
A9: Customer | B9: Parcel protection | C9: Optional cover for loss or damage up to ₦50,000 (+₦500).
A10: Customer | B10: Live map | C10: Rider, receiver and pickup point on the map, with ETA and distance left.
A11: Customer | B11: Delivery PIN | C11: A 4-digit code the receiver gives the rider at handover.
A12: Customer | B12: Chat and call | C12: Message the rider in-app and call them on the number they entered.
A13: Customer | B13: Receipt and timeline | C13: Five-step tracking history and an itemised receipt.
A14: Customer | B14: Share trip and Safety | C14: Copy a live trip link, or open the safety sheet with the 112 emergency line.
A15: Customer | B15: Location sharing | C15: Turn the receiver's live location on or off.
... A28: Both | B28: Role switch | C28: Switch between the customer and rider apps from Profile.
